MANIFEST.in
README.rst
setup.cfg
setup.py
invitations/__init__.py
invitations/bootstrap.py
invitations/helpers.py
invitations/controllers/__init__.py
invitations/controllers/root.py
invitations/lib/__init__.py
invitations/lib/forms.py
invitations/lib/helpers.py
invitations/lib/validators.py
invitations/model/__init__.py
invitations/model/ming/__init__.py
invitations/model/ming/models.py
invitations/model/sqla/__init__.py
invitations/model/sqla/models.py
invitations/public/__init__.py
invitations/public/css/style.css
invitations/public/images/star.png
invitations/templates/__init__.py
invitations/templates/activate.xhtml
invitations/templates/create.xhtml
invitations/templates/index.xhtml
tgapp_invitations.egg-info/PKG-INFO
tgapp_invitations.egg-info/SOURCES.txt
tgapp_invitations.egg-info/dependency_links.txt
tgapp_invitations.egg-info/entry_points.txt
tgapp_invitations.egg-info/not-zip-safe
tgapp_invitations.egg-info/requires.txt
tgapp_invitations.egg-info/top_level.txt