Metadata-Version: 1.0
Name: tgapp-invitations
Version: 0.2.5
Summary: Provides a way to invite new users into a TurboGears2 application
Home-page: https://github.com/axant/tgapp-invitations
Author: Axant, Vincenzo Castiglia
Author-email: vincenzo.castiglia@axant.it
License: UNKNOWN
Keywords: turbogears2.application
Platform: UNKNOWN
